papertrades/__init__.py
papertrades/core.py
papertrades-1.0.7.dist-info/METADATA
papertrades-1.0.7.dist-info/WHEEL
papertrades-1.0.7.dist-info/top_level.txt
papertrades-1.0.7.dist-info/RECORD
