Metadata-Version: 2.4
Name: papertrades
Version: 1.0.7
Summary: a package to simulate and analyze paper trades in Python
Author: Kevin Zhu
Author-email: kzhu2099@gmail.com
Maintainer: Kevin Zhu
Maintainer-email: kzhu2099@gmail.com
License: MIT License
Project-URL: Homepage, https://github.com/kzhu2099/Paper-Trades
Project-URL: Issues, https://github.com/kzhu2099/Paper-Trades/issues
Classifier: Development Status :: 4 - Beta
Classifier: Intended Audience :: End Users/Desktop
Classifier: License :: OSI Approved :: MIT License
Classifier: Natural Language :: English
Classifier: Operating System :: OS Independent
Classifier: Programming Language :: Python :: 3
Requires-Python: >=3.9
Requires-Dist: matplotlib
Requires-Dist: pandas
